hypothesis_geojson/__init__.py
hypothesis_geojson/scripts/__init__.py
hypothesis_geojson/scripts/edge_features.py
hypothesis_geojson-0.1.dist-info/DESCRIPTION.rst
hypothesis_geojson-0.1.dist-info/METADATA
hypothesis_geojson-0.1.dist-info/RECORD
hypothesis_geojson-0.1.dist-info/WHEEL
hypothesis_geojson-0.1.dist-info/entry_points.txt
hypothesis_geojson-0.1.dist-info/metadata.json
hypothesis_geojson-0.1.dist-info/top_level.txt
